pyloc/__init__.py
pyloc/pyloc.py
py_geo_loc-1.0.0.dist-info/METADATA
py_geo_loc-1.0.0.dist-info/WHEEL
py_geo_loc-1.0.0.dist-info/top_level.txt
py_geo_loc-1.0.0.dist-info/RECORD
