Metadata-Version: 2.1
Name: py-geo-loc
Version: 1.0.0
Summary: A Python Package to get the latitude and longitude of a location
Home-page: UNKNOWN
Author: Ramananda Kairi
Author-email: ramanandakairi@gmail.com
License: MIT
Platform: UNKNOWN
Requires-Dist: requests
